Metadata-Version: 1.0
Name: prob-dist-timi
Version: 1.0
Summary: Gaussian and Binomial distributions
Home-page: UNKNOWN
Author: Olusegun Timilehin
Author-email: UNKNOWN
License: UNKNOWN
Platform: UNKNOWN
